echomind/__init__.py
echomind/apple_podcast_ch.py
echomind/apple_podcast_en.py
echomind/cli_ch.py
echomind/cli_en.py
echomind/visual_ch.py
echomind/visual_en.py
echomind/youtube_ch.py
echomind/youtube_en.py
echomind-1.0.0.dist-info/licenses/LICENSE
echomind-1.0.0.dist-info/METADATA
echomind-1.0.0.dist-info/WHEEL
echomind-1.0.0.dist-info/entry_points.txt
echomind-1.0.0.dist-info/top_level.txt
echomind-1.0.0.dist-info/RECORD
