Metadata-Version: 2.4
Name: echomind
Version: 1.0.0
Summary: 播客转录与摘要工具，支持 Apple Podcast 和 YouTube 平台
Home-page: https://github.com/henryzha/echomind
Author: EchoMind Team
Author-email: EchoMind Team <contact@echomind.app>
Maintainer-email: EchoMind Team <contact@echomind.app>
License: MIT
Project-URL: Homepage, https://github.com/henryzha/echomind
Project-URL: Repository, https://github.com/henryzha/echomind.git
Project-URL: Documentation, https://github.com/henryzha/echomind#readme
Project-URL: Bug Tracker, https://github.com/henryzha/echomind/issues
Keywords: podcast,transcription,summary,youtube,apple podcast,whisper,ai
Classifier: Development Status :: 4 - Beta
Classifier: Intended Audience :: End Users/Desktop
Classifier: Topic :: Multimedia :: Sound/Audio
Classifier: License :: OSI Approved :: MIT License
Classifier: Programming Language :: Python :: 3
Classifier: Programming Language :: Python :: 3.8
Classifier: Programming Language :: Python :: 3.9
Classifier: Programming Language :: Python :: 3.10
Classifier: Programming Language :: Python :: 3.11
Classifier: Programming Language :: Python :: 3.12
Classifier: Operating System :: OS Independent
Requires-Python: >=3.8
License-File: LICENSE
Requires-Dist: requests
Requires-Dist: feedparser>=6.0.0
Requires-Dist: python-dotenv
Requires-Dist: google-generativeai
Requires-Dist: beautifulsoup4
Requires-Dist: tqdm
Requires-Dist: mlx-whisper
Requires-Dist: groq
Requires-Dist: openai-whisper
Requires-Dist: youtube-transcript-api
Requires-Dist: yt-dlp
Dynamic: author
Dynamic: home-page
Dynamic: license-file
Dynamic: requires-python
